vehicle_makes/__init__.py
vehicle_makes/vehicle_makes.py
vehicle_makes-0.1.0.dist-info/LICENSE
vehicle_makes-0.1.0.dist-info/METADATA
vehicle_makes-0.1.0.dist-info/WHEEL
vehicle_makes-0.1.0.dist-info/top_level.txt
vehicle_makes-0.1.0.dist-info/RECORD
