Metadata-Version: 2.1
Name: vehicle-makes
Version: 0.1.0
Summary: Python library to provide up-to-date vehicle make and model data
Home-page: https://code.richard.do/richardARPANET/vehicle-makes/
Author: Richard O'Dwyer
Author-email: richard@richard.do
License: Apache 2.0
Platform: UNKNOWN
Classifier: Intended Audience :: Developers
Classifier: Operating System :: OS Independent
Classifier: Programming Language :: Python
Classifier: Programming Language :: Python :: 3
Classifier: Programming Language :: Python :: 3.6
Classifier: Programming Language :: Python :: 3.7
Classifier: Topic :: Internet :: WWW/HTTP
Requires-Dist: requests
Requires-Dist: requests-futures
